{"stats":{"minecraft:killed_by":{"advanced_nextbot_mod:amogus":1,"advanced_nextbot_mod:cursed_steve":28,"advanced_nextbot_mod:quandaledingle":1},"minecraft:custom":{"minecraft:jump":174,"minecraft:time_since_rest":34,"minecraft:walk_on_water_one_cm":114,"minecraft:crouch_one_cm":1178,"minecraft:play_one_minute":5287,"minecraft:deaths":30,"minecraft:sprint_one_cm":39474,"minecraft:damage_taken":422649,"minecraft:time_since_death":2,"minecraft:walk_one_cm":23398,"minecraft:sneak_time":390,"minecraft:fall_one_cm":6734,"minecraft:fly_one_cm":100452}},"DataVersion":2586}