{
  "display": {
    "icon": {
      "item": "minecraft:coal_block"
    },
    "title": {
      "text": "Gas Leak in Terraville"
    },
    "description": {
      "text": "\"I did that!\"",
      "extra": [
        {
          "text": "\n\n5 Points",
          "color": "gold"
        }
      ]
    },
    "frame": "task",
    "show_toast": true,
    "announce_to_chat": true,
    "hidden": false
  },
  "parent": "owza_advancements:swamped_town",
  "criteria": {
    "gasStation": {
      "trigger": "minecraft:impossible"
    }
  },
  "rewards": {
    "function": "owza_functions:rewards/gas_leak"
  }
}
