{
  "display": {
    "icon": {
      "item": "minecraft:player_head",
      "nbt": "{SkullOwner:{Id:[I;469585196,-349222809,-2067176579,-172447485],Name:\"Thermal Goggles\",Properties:{textures:[{Value:\"eyJ0ZXh0dXJlcyI6eyJTS0lOIjp7InVybCI6Imh0dHA6Ly90ZXh0dXJlcy5taW5lY3JhZnQubmV0L3RleHR1cmUvZWViYTk0N2M3YWQ1OTJjMWNlOWU5ZTgyMTE2YWI4MzBmNzA2NWU5NDM1NjdjZjQxZjYwYWVmZjk3NzEyN2IyNiJ9fX0=\"}]}}}"
    },
    "title": {
      "text": "Ultraviolet Vision"
    },
    "description": {
      "text": "Obtain Thermal Goggles",
      "extra": [
        {
          "text": "\n\n5 Points",
          "color": "gold"
        }
      ]
    },
    "frame": "task",
    "show_toast": true,
    "announce_to_chat": true,
    "hidden": false
  },
  "parent": "owza_advancements:bravo_6_going_dark",
  "criteria": {
    "thermals": {
      "trigger": "minecraft:inventory_changed",
      "conditions": {
        "player": {
          "equipment": {
            "head": {
              "items": [
                "minecraft:player_head"
              ],
              "nbt": "{display:{Name:'{\"text\":\"Thermal Goggles\"}'}}"
            }
          }
        }
      }
    }
  },
  "rewards": {
    "function": "owza_functions:rewards/ultraviolet_vision"
  }
}
